README.rst
setup.py
ogPypeline/__init__.py
ogPypeline/drilling.py
ogPypeline/fluid.py
ogPypeline/force_and_power.py
ogPypeline/gas.py
ogPypeline/general.py
ogPypeline/production.py
ogPypeline.egg-info/PKG-INFO
ogPypeline.egg-info/SOURCES.txt
ogPypeline.egg-info/dependency_links.txt
ogPypeline.egg-info/top_level.txt