Metadata-Version: 2.1
Name: ogPypeline
Version: 0.0.3
Summary: Unit conversion for oil and gas calculations
Home-page: https://github.com/this-isnt-me/ogPypeline
Author: Tim Clarke
Author-email: <info@hitchadvisor.info>
License: MIT
Keywords: python,engineering,oil,gas,energy,unit,conversion
Platform: UNKNOWN
Classifier: Development Status :: 3 - Alpha
Classifier: Intended Audience :: Developers
Classifier: Programming Language :: Python :: 3
Classifier: Operating System :: Unix
Classifier: Operating System :: MacOS :: MacOS X
Classifier: Operating System :: Microsoft :: Windows
